lvmpwi/__init__.py
lvmpwi/__main__.py
lvmpwi/actor/__init__.py
lvmpwi/actor/actor.py
lvmpwi/actor/commands/__init__.py
lvmpwi/actor/commands/mount.py
lvmpwi/actor/commands/pointing_model.py
lvmpwi/actor/commands/site.py
lvmpwi/actor/commands/status.py
lvmpwi/actor/exceptions.py
lvmpwi/etc/lvm.pwi.yml
lvmpwi/pwi/__init__.py
lvmpwi/pwi/platesolve.py
lvmpwi/pwi/pwi4_build_model.py
lvmpwi/pwi/pwi4_client.py
lvmpwi/pwi/pwi4_client_demo.py
sdss_lvmpwi-0.0.42.dist-info/LICENSE
sdss_lvmpwi-0.0.42.dist-info/METADATA
sdss_lvmpwi-0.0.42.dist-info/WHEEL
sdss_lvmpwi-0.0.42.dist-info/entry_points.txt
sdss_lvmpwi-0.0.42.dist-info/RECORD
