Metadata-Version: 2.3
Name: sdss-lvmpwi
Version: 0.0.42
Summary: Lvm Pwi4 Actor
License: BSD-3-Clause
Keywords: astronomy,software
Author: Florian Briegel
Author-email: briegel@mpia.de
Requires-Python: >=3.8,<4.0
Classifier: Intended Audience :: Science/Research
Classifier: License :: OSI Approved :: BSD License
Classifier: Natural Language :: English
Classifier: Operating System :: OS Independent
Classifier: Programming Language :: Python :: 3
Classifier: Programming Language :: Python :: 3.8
Classifier: Programming Language :: Python :: 3.9
Classifier: Programming Language :: Python :: 3.10
Classifier: Programming Language :: Python :: 3.11
Classifier: Programming Language :: Python :: 3.12
Classifier: Programming Language :: Python :: 3.13
Classifier: Topic :: Documentation :: Sphinx
Classifier: Topic :: Software Development :: Libraries :: Python Modules
Provides-Extra: docs
Requires-Dist: click-default-group (>=1.2.2,<2.0.0)
Requires-Dist: daemonocle (>=1.1.1,<2.0.0)
Requires-Dist: sdss-clu (>=2.0.0)
Requires-Dist: sdss-cluplus (>=0.5.0)
Requires-Dist: sdsstools (>=0.4.0)
Project-URL: Documentation, https://sdss-lvmpwi.readthedocs.org
Project-URL: Homepage, https://github.com/sdss/lvmpwi
Project-URL: Repository, https://github.com/sdss/lvmpwi
